{
	"info": {
		"_postman_id": "6431d2a4-ca33-448e-9bd2-a80afcb53989",
		"name": "laravel-books-shop-simple",
		"schema": "https://schema.getpostman.com/json/collection/v2.1.0/collection.json",
		"_exporter_id": "21008900"
	},
	"item": [
		{
			"name": "ADMIN",
			"item": [
				{
					"name": "BOOK",
					"item": [
						{
							"name": "GET/BOOK",
							"request": {
								"auth": {
									"type": "bearer",
									"bearer": [
										{
											"key": "token",
											"value": "3|0FcSFtScNvO8rKxuesX1lRZUSVCdv1sh97ZdAxw5",
											"type": "string"
										}
									]
								},
								"method": "GET",
								"header": [],
								"url": {
									"raw": "localhost:8000/api/admin/book",
									"host": [
										"localhost"
									],
									"port": "8000",
									"path": [
										"api",
										"admin",
										"book"
									]
								}
							},
							"response": []
						},
						{
							"name": "POST/BOOK",
							"request": {
								"auth": {
									"type": "bearer",
									"bearer": [
										{
											"key": "token",
											"value": "3|0FcSFtScNvO8rKxuesX1lRZUSVCdv1sh97ZdAxw5",
											"type": "string"
										}
									]
								},
								"method": "POST",
								"header": [],
								"body": {
									"mode": "formdata",
									"formdata": [
										{
											"key": "name",
											"value": "true love",
											"type": "text"
										},
										{
											"key": "description",
											"value": "story about benjamin4k with zooane",
											"type": "text"
										},
										{
											"key": "price",
											"value": "50000",
											"type": "text"
										},
										{
											"key": "stok",
											"value": "1",
											"type": "text"
										},
										{
											"key": "image",
											"type": "file",
											"src": []
										}
									]
								},
								"url": {
									"raw": "localhost:8000/api/admin/book",
									"host": [
										"localhost"
									],
									"port": "8000",
									"path": [
										"api",
										"admin",
										"book"
									]
								}
							},
							"response": []
						},
						{
							"name": "GET/BOOK/ID",
							"request": {
								"auth": {
									"type": "bearer",
									"bearer": [
										{
											"key": "token",
											"value": "3|0FcSFtScNvO8rKxuesX1lRZUSVCdv1sh97ZdAxw5",
											"type": "string"
										}
									]
								},
								"method": "GET",
								"header": [],
								"url": {
									"raw": "localhost:8000/api/admin/book/1",
									"host": [
										"localhost"
									],
									"port": "8000",
									"path": [
										"api",
										"admin",
										"book",
										"1"
									]
								}
							},
							"response": []
						},
						{
							"name": "PUT/BOOK/ID",
							"request": {
								"auth": {
									"type": "bearer",
									"bearer": [
										{
											"key": "token",
											"value": "3|0FcSFtScNvO8rKxuesX1lRZUSVCdv1sh97ZdAxw5",
											"type": "string"
										}
									]
								},
								"method": "PUT",
								"header": [
									{
										"key": "email",
										"value": "zooane123@gmail.com",
										"type": "text"
									}
								],
								"body": {
									"mode": "formdata",
									"formdata": [
										{
											"key": "price",
											"value": "165000",
											"type": "text"
										}
									]
								},
								"url": {
									"raw": "localhost:8000/api/admin/book/1",
									"host": [
										"localhost"
									],
									"port": "8000",
									"path": [
										"api",
										"admin",
										"book",
										"1"
									]
								}
							},
							"response": []
						},
						{
							"name": "DESTROY/BOOK/ID",
							"request": {
								"auth": {
									"type": "bearer",
									"bearer": [
										{
											"key": "token",
											"value": "3|0FcSFtScNvO8rKxuesX1lRZUSVCdv1sh97ZdAxw5",
											"type": "string"
										}
									]
								},
								"method": "DELETE",
								"header": [],
								"url": {
									"raw": "localhost:8000/api/admin/book/1",
									"host": [
										"localhost"
									],
									"port": "8000",
									"path": [
										"api",
										"admin",
										"book",
										"1"
									]
								}
							},
							"response": []
						}
					]
				},
				{
					"name": "ACCOUNT",
					"item": [
						{
							"name": "GET/ACCOUNT",
							"request": {
								"auth": {
									"type": "bearer",
									"bearer": [
										{
											"key": "token",
											"value": "3|0FcSFtScNvO8rKxuesX1lRZUSVCdv1sh97ZdAxw5",
											"type": "string"
										}
									]
								},
								"method": "GET",
								"header": [],
								"url": {
									"raw": "localhost:8000/api/admin/account",
									"host": [
										"localhost"
									],
									"port": "8000",
									"path": [
										"api",
										"admin",
										"account"
									]
								}
							},
							"response": []
						},
						{
							"name": "POST/ACCOUNT",
							"request": {
								"auth": {
									"type": "bearer",
									"bearer": [
										{
											"key": "token",
											"value": "3|0FcSFtScNvO8rKxuesX1lRZUSVCdv1sh97ZdAxw5",
											"type": "string"
										}
									]
								},
								"method": "POST",
								"header": [],
								"body": {
									"mode": "formdata",
									"formdata": [
										{
											"key": "username",
											"value": "zooane",
											"type": "text"
										},
										{
											"key": "email",
											"value": "zooane@gmail.com",
											"type": "text"
										},
										{
											"key": "password",
											"value": "password",
											"type": "text"
										},
										{
											"key": "password_confirmation",
											"value": "password",
											"type": "text"
										}
									]
								},
								"url": {
									"raw": "localhost:8000/api/admin/account",
									"host": [
										"localhost"
									],
									"port": "8000",
									"path": [
										"api",
										"admin",
										"account"
									]
								}
							},
							"response": []
						},
						{
							"name": "GET/ACCOUNT/ID",
							"request": {
								"auth": {
									"type": "bearer",
									"bearer": [
										{
											"key": "token",
											"value": "3|0FcSFtScNvO8rKxuesX1lRZUSVCdv1sh97ZdAxw5",
											"type": "string"
										}
									]
								},
								"method": "GET",
								"header": [],
								"url": {
									"raw": "localhost:8000/api/admin/account/1",
									"host": [
										"localhost"
									],
									"port": "8000",
									"path": [
										"api",
										"admin",
										"account",
										"1"
									]
								}
							},
							"response": []
						},
						{
							"name": "PUT/ACCOUNT/ID",
							"request": {
								"auth": {
									"type": "bearer",
									"bearer": [
										{
											"key": "token",
											"value": "3|0FcSFtScNvO8rKxuesX1lRZUSVCdv1sh97ZdAxw5",
											"type": "string"
										}
									]
								},
								"method": "PUT",
								"header": [
									{
										"key": "email",
										"value": "zooane123@gmail.com",
										"type": "text"
									}
								],
								"body": {
									"mode": "formdata",
									"formdata": [
										{
											"key": "username",
											"value": "zooanez",
											"type": "text"
										}
									]
								},
								"url": {
									"raw": "localhost:8000/api/admin/account/1",
									"host": [
										"localhost"
									],
									"port": "8000",
									"path": [
										"api",
										"admin",
										"account",
										"1"
									]
								}
							},
							"response": []
						},
						{
							"name": "DESTROY/ACCOUNT/ID",
							"request": {
								"auth": {
									"type": "bearer",
									"bearer": [
										{
											"key": "token",
											"value": "3|0FcSFtScNvO8rKxuesX1lRZUSVCdv1sh97ZdAxw5",
											"type": "string"
										}
									]
								},
								"method": "DELETE",
								"header": [],
								"url": {
									"raw": "localhost:8000/api/admin/account/1",
									"host": [
										"localhost"
									],
									"port": "8000",
									"path": [
										"api",
										"admin",
										"account",
										"1"
									]
								}
							},
							"response": []
						}
					]
				},
				{
					"name": "TRANSACTION",
					"item": [
						{
							"name": "GET/TRANSACTION",
							"request": {
								"auth": {
									"type": "bearer",
									"bearer": [
										{
											"key": "token",
											"value": "3|0FcSFtScNvO8rKxuesX1lRZUSVCdv1sh97ZdAxw5",
											"type": "string"
										}
									]
								},
								"method": "GET",
								"header": [],
								"url": {
									"raw": "localhost:8000/api/admin/transaction",
									"host": [
										"localhost"
									],
									"port": "8000",
									"path": [
										"api",
										"admin",
										"transaction"
									]
								}
							},
							"response": []
						},
						{
							"name": "POST/TRANSACTION",
							"request": {
								"auth": {
									"type": "bearer",
									"bearer": [
										{
											"key": "token",
											"value": "3|0FcSFtScNvO8rKxuesX1lRZUSVCdv1sh97ZdAxw5",
											"type": "string"
										}
									]
								},
								"method": "POST",
								"header": [],
								"body": {
									"mode": "formdata",
									"formdata": [
										{
											"key": "user_id",
											"value": "1",
											"type": "text"
										},
										{
											"key": "book_id",
											"value": "2",
											"type": "text"
										},
										{
											"key": "quantity",
											"value": "1",
											"type": "text"
										},
										{
											"key": "total_payment",
											"value": "50000",
											"type": "text"
										},
										{
											"key": "payment_date",
											"value": "05-12-2022",
											"type": "text"
										}
									]
								},
								"url": {
									"raw": "localhost:8000/api/admin/transaction",
									"host": [
										"localhost"
									],
									"port": "8000",
									"path": [
										"api",
										"admin",
										"transaction"
									]
								}
							},
							"response": []
						},
						{
							"name": "GET/TRANSACTION/ID",
							"request": {
								"auth": {
									"type": "bearer",
									"bearer": [
										{
											"key": "token",
											"value": "3|0FcSFtScNvO8rKxuesX1lRZUSVCdv1sh97ZdAxw5",
											"type": "string"
										}
									]
								},
								"method": "GET",
								"header": [],
								"url": {
									"raw": "localhost:8000/api/admin/transaction/1",
									"host": [
										"localhost"
									],
									"port": "8000",
									"path": [
										"api",
										"admin",
										"transaction",
										"1"
									]
								}
							},
							"response": []
						},
						{
							"name": "PUT/TRANSACTION/ID",
							"request": {
								"auth": {
									"type": "bearer",
									"bearer": [
										{
											"key": "token",
											"value": "3|0FcSFtScNvO8rKxuesX1lRZUSVCdv1sh97ZdAxw5",
											"type": "string"
										}
									]
								},
								"method": "PUT",
								"header": [
									{
										"key": "email",
										"value": "zooane123@gmail.com",
										"type": "text"
									}
								],
								"body": {
									"mode": "formdata",
									"formdata": [
										{
											"key": "total_price",
											"value": "35000",
											"type": "text"
										}
									]
								},
								"url": {
									"raw": "localhost:8000/api/admin/transaction/1",
									"host": [
										"localhost"
									],
									"port": "8000",
									"path": [
										"api",
										"admin",
										"transaction",
										"1"
									]
								}
							},
							"response": []
						},
						{
							"name": "DESTROY/TRANSACTION/ID",
							"request": {
								"auth": {
									"type": "bearer",
									"bearer": [
										{
											"key": "token",
											"value": "3|0FcSFtScNvO8rKxuesX1lRZUSVCdv1sh97ZdAxw5",
											"type": "string"
										}
									]
								},
								"method": "DELETE",
								"header": [],
								"url": {
									"raw": "localhost:8000/api/admin/transaction/1",
									"host": [
										"localhost"
									],
									"port": "8000",
									"path": [
										"api",
										"admin",
										"transaction",
										"1"
									]
								}
							},
							"response": []
						}
					]
				}
			]
		},
		{
			"name": "USER",
			"item": [
				{
					"name": "BOOK",
					"item": [
						{
							"name": "GET/BOOK",
							"request": {
								"auth": {
									"type": "bearer",
									"bearer": [
										{
											"key": "token",
											"value": "3|0FcSFtScNvO8rKxuesX1lRZUSVCdv1sh97ZdAxw5",
											"type": "string"
										}
									]
								},
								"method": "GET",
								"header": [],
								"url": {
									"raw": "localhost:8000/api/user/book",
									"host": [
										"localhost"
									],
									"port": "8000",
									"path": [
										"api",
										"user",
										"book"
									]
								}
							},
							"response": []
						},
						{
							"name": "GET/BOOK/ID",
							"request": {
								"auth": {
									"type": "bearer",
									"bearer": [
										{
											"key": "token",
											"value": "3|0FcSFtScNvO8rKxuesX1lRZUSVCdv1sh97ZdAxw5",
											"type": "string"
										}
									]
								},
								"method": "GET",
								"header": [],
								"url": {
									"raw": "localhost:8000/api/user/book/1",
									"host": [
										"localhost"
									],
									"port": "8000",
									"path": [
										"api",
										"user",
										"book",
										"1"
									]
								}
							},
							"response": []
						}
					]
				},
				{
					"name": "ACCOUNT",
					"item": [
						{
							"name": "GET/ACCOUNT",
							"request": {
								"method": "GET",
								"header": [],
								"url": {
									"raw": "localhost:8000/api/user/account",
									"host": [
										"localhost"
									],
									"port": "8000",
									"path": [
										"api",
										"user",
										"account"
									]
								}
							},
							"response": []
						}
					]
				},
				{
					"name": "PAYMENT",
					"item": [
						{
							"name": "POST/BUY",
							"request": {
								"auth": {
									"type": "bearer",
									"bearer": [
										{
											"key": "token",
											"value": "3|0FcSFtScNvO8rKxuesX1lRZUSVCdv1sh97ZdAxw5",
											"type": "string"
										}
									]
								},
								"method": "POST",
								"header": [],
								"body": {
									"mode": "formdata",
									"formdata": [
										{
											"key": "shoe",
											"value": "1",
											"type": "text"
										},
										{
											"key": "quantity",
											"value": "2",
											"type": "text"
										}
									]
								},
								"url": {
									"raw": "localhost:8000/api/user/buy",
									"host": [
										"localhost"
									],
									"port": "8000",
									"path": [
										"api",
										"user",
										"buy"
									]
								}
							},
							"response": []
						}
					]
				},
				{
					"name": "TRANSACTION",
					"item": [
						{
							"name": "GET/TRANSACTION",
							"request": {
								"auth": {
									"type": "bearer",
									"bearer": [
										{
											"key": "token",
											"value": "3|0FcSFtScNvO8rKxuesX1lRZUSVCdv1sh97ZdAxw5",
											"type": "string"
										}
									]
								},
								"method": "GET",
								"header": [],
								"url": {
									"raw": "localhost:8000/api/user/transaction",
									"host": [
										"localhost"
									],
									"port": "8000",
									"path": [
										"api",
										"user",
										"transaction"
									]
								}
							},
							"response": []
						},
						{
							"name": "GET/TRANSACTION/ID",
							"request": {
								"auth": {
									"type": "bearer",
									"bearer": [
										{
											"key": "token",
											"value": "3|0FcSFtScNvO8rKxuesX1lRZUSVCdv1sh97ZdAxw5",
											"type": "string"
										}
									]
								},
								"method": "GET",
								"header": [],
								"url": {
									"raw": "localhost:8000/api/user/transaction/1",
									"host": [
										"localhost"
									],
									"port": "8000",
									"path": [
										"api",
										"user",
										"transaction",
										"1"
									]
								}
							},
							"response": []
						}
					]
				}
			]
		},
		{
			"name": "AUTH",
			"item": [
				{
					"name": "POST/LOGIN",
					"request": {
						"method": "POST",
						"header": [],
						"body": {
							"mode": "formdata",
							"formdata": [
								{
									"key": "username",
									"value": "benjamin4k",
									"type": "text"
								},
								{
									"key": "password",
									"value": "password",
									"type": "text"
								}
							]
						},
						"url": {
							"raw": "localhost:8000/api/login",
							"host": [
								"localhost"
							],
							"port": "8000",
							"path": [
								"api",
								"login"
							]
						}
					},
					"response": []
				},
				{
					"name": "POST/LOGOUT",
					"request": {
						"method": "POST",
						"header": [],
						"url": {
							"raw": "localhost:8000/api/logout",
							"host": [
								"localhost"
							],
							"port": "8000",
							"path": [
								"api",
								"logout"
							]
						}
					},
					"response": []
				},
				{
					"name": "POST/REGISTER",
					"request": {
						"method": "POST",
						"header": [],
						"body": {
							"mode": "formdata",
							"formdata": [
								{
									"key": "username",
									"value": "benjamin4k",
									"type": "text"
								},
								{
									"key": "email",
									"value": "benjamin@gmail.com",
									"type": "text"
								},
								{
									"key": "password",
									"value": "password",
									"type": "text"
								},
								{
									"key": "password_confirmation",
									"value": "password",
									"type": "text"
								}
							]
						},
						"url": {
							"raw": "localhost:8000/api/register",
							"host": [
								"localhost"
							],
							"port": "8000",
							"path": [
								"api",
								"register"
							]
						}
					},
					"response": []
				}
			]
		},
		{
			"name": "GET/INDEX",
			"request": {
				"method": "GET",
				"header": [],
				"url": {
					"raw": "localhost:8000/api",
					"host": [
						"localhost"
					],
					"port": "8000",
					"path": [
						"api"
					]
				}
			},
			"response": []
		}
	]
}